odoo/addons/stock_delivery_note/README.rst
odoo/addons/stock_delivery_note/__init__.py
odoo/addons/stock_delivery_note/__manifest__.py
odoo/addons/stock_delivery_note/i18n/es.po
odoo/addons/stock_delivery_note/i18n/fr.po
odoo/addons/stock_delivery_note/i18n/hr.po
odoo/addons/stock_delivery_note/i18n/it.po
odoo/addons/stock_delivery_note/i18n/nl.po
odoo/addons/stock_delivery_note/i18n/nl_NL.po
odoo/addons/stock_delivery_note/i18n/stock_delivery_note.pot
odoo/addons/stock_delivery_note/models/__init__.py
odoo/addons/stock_delivery_note/models/stock_picking.py
odoo/addons/stock_delivery_note/readme/CONTRIBUTORS.md
odoo/addons/stock_delivery_note/readme/DESCRIPTION.md
odoo/addons/stock_delivery_note/readme/USAGE.md
odoo/addons/stock_delivery_note/reports/report_picking.xml
odoo/addons/stock_delivery_note/static/description/icon.png
odoo/addons/stock_delivery_note/static/description/index.html
odoo/addons/stock_delivery_note/views/stock_picking.xml
odoo_addon_stock_delivery_note-18.0.1.0.0.2.dist-info/METADATA
odoo_addon_stock_delivery_note-18.0.1.0.0.2.dist-info/WHEEL
odoo_addon_stock_delivery_note-18.0.1.0.0.2.dist-info/top_level.txt
odoo_addon_stock_delivery_note-18.0.1.0.0.2.dist-info/RECORD
