Metadata-Version: 2.1
Name: odoo-addon-stock_delivery_note
Version: 18.0.1.0.0.2
Requires-Python: >=3.10
Requires-Dist: odoo==18.0.*
Summary: This module allows to fill in a delivery note that will be displayed on delivery report
Home-page: https://github.com/OCA/stock-logistics-reporting
License: AGPL-3
Author: ACSONE SA/NV,Odoo Community Association (OCA)
Author-email: support@odoo-community.org
Classifier: Programming Language :: Python
Classifier: Framework :: Odoo
Classifier: Framework :: Odoo :: 18.0
Classifier: License :: OSI Approved :: GNU Affero General Public License v3
